MANIFEST.in
README.rst
setup.py
quickgui/__init__.py
quickgui/prepublish.py
quickgui/quickgui.py
quickgui/version.py
quickgui.egg-info/PKG-INFO
quickgui.egg-info/SOURCES.txt
quickgui.egg-info/dependency_links.txt
quickgui.egg-info/top_level.txt