Metadata-Version: 1.1
Name: quickgui
Version: 1.4.3
Summary: Rapidly create gui without any knowledge of wxpython
Home-page: https://pypi.python.org/pypi/quickgui
Author: Jerry
Author-email: jerryzhujian9@gmail.com
License: MIT
Keywords: gui,pyside,pyqt,easygui,cross-platform,quick,easy,wrapper
Platform: UNKNOWN
Classifier: Development Status :: 3 - Alpha
Classifier: Intended Audience :: Developers
Classifier: Topic :: Software Development :: Build Tools
Classifier: License :: OSI Approved :: MIT License
Classifier: Programming Language :: Python :: 2.7
